chivel/__init__.py
chivel/_recorder.py
chivel/archive.dll
chivel/bz2.dll
chivel/chivel.pyd
chivel/chivel.pyi
chivel/gif.dll
chivel/jpeg62.dll
chivel/leptonica-1.85.0.dll
chivel/libcrypto-3-x64.dll
chivel/libcurl.dll
chivel/liblzma.dll
chivel/libpng16.dll
chivel/libsharpyuv.dll
chivel/libssl-3-x64.dll
chivel/libwebp.dll
chivel/libwebpdecoder.dll
chivel/libwebpdemux.dll
chivel/libwebpmux.dll
chivel/libxml2.dll
chivel/lz4.dll
chivel/opencv_world4110.dll
chivel/openjp2.dll
chivel/tesseract55.dll
chivel/tiff.dll
chivel/turbojpeg.dll
chivel/zlib1.dll
chivel/zstd.dll
chivel/tessdata/eng.traineddata
chivel-0.6.3.dist-info/METADATA
chivel-0.6.3.dist-info/WHEEL
chivel-0.6.3.dist-info/top_level.txt
chivel-0.6.3.dist-info/RECORD
