Metadata-Version: 2.4
Name: chivel
Version: 0.6.3
Summary: For easily interfacing with the screen, just as a human would.
Author: Mitchell Talyat
Classifier: Programming Language :: Python :: 3.13
Classifier: Programming Language :: Python :: 3 :: Only
Classifier: Operating System :: Microsoft :: Windows
Requires-Python: ==3.13.*
Dynamic: author
Dynamic: classifier
Dynamic: description
Dynamic: description-content-type
Dynamic: requires-python
Dynamic: summary
